devtools_color_picker/__init__.py
devtools_color_picker-1.0.1.dist-info/METADATA
devtools_color_picker-1.0.1.dist-info/WHEEL
devtools_color_picker-1.0.1.dist-info/top_level.txt
devtools_color_picker-1.0.1.dist-info/RECORD
