Metadata-Version: 2.1
Name: devtools_color_picker
Version: 1.0.1
Summary: Color picker tool
Home-page: https://devtools.at/tools/color-picker
Author: DevTools.at
Author-email: hello@devtools.at
Project-URL: Homepage, https://devtools.at/tools/color-picker
Project-URL: Repository, https://github.com/devtools-at/color-picker
Classifier: Development Status :: 4 - Beta
Classifier: Intended Audience :: Developers
Classifier: License :: OSI Approved :: MIT License
Classifier: Programming Language :: Python :: 3
Requires-Python: >=3.8
